<?xml version = '1.0' encoding = 'UTF-8'?>
<FKIndexAssociation class="oracle.dbtools.crest.model.design.relational.FKIndexAssociation" directorySegmentName="seg_1" id="B7156EB8-41C0-DDD1-20A9-99C0663540BD" containerWithKeyObject="3DDFB9A0-5B68-6F8D-CC86-A7DF6F9044EF" localFKIndex="BC805CD0-31E2-8359-989F-C9B40D8292AE" name="ENVCONDITION_ENVSUBJCODE_FK">
<createdBy>BondS</createdBy>
<createdTime>2020-01-23 14:21:18 UTC</createdTime>
<ownerDesignName>BDF_Aug</ownerDesignName>
<referredTableLongName>ENVSUBJCODE</referredTableLongName>
<deleteRule>NO ACTION</deleteRule>
<referredTableID>1502FD8F-45C7-E37C-54B1-1B13E1B8679A</referredTableID>
<keyObject>D555AFE0-87F4-9978-DD3D-F18992548C22</keyObject>
<referredKeyID>D555AFE0-87F4-9978-DD3D-F18992548C22</referredKeyID>
<mandatory>false</mandatory>
<refColNames>ENV_SUBJ_ID</refColNames>
<transferable>true</transferable>
<rely>false</rely>
<columnDependencyConstraintGenerateInDDL>true</columnDependencyConstraintGenerateInDDL>
</FKIndexAssociation>